jobcli.py
jobcli-0.1b2.dist-info/DESCRIPTION.rst
jobcli-0.1b2.dist-info/METADATA
jobcli-0.1b2.dist-info/RECORD
jobcli-0.1b2.dist-info/WHEEL
jobcli-0.1b2.dist-info/entry_points.txt
jobcli-0.1b2.dist-info/metadata.json
jobcli-0.1b2.dist-info/top_level.txt
